impgrpc/__init__.py
impgrpc/__main__.py
impgrpc/aio/__init__.py
impgrpc/aio/async_client.py
impgrpc/client.py
impgrpc/common.py
impgrpc/compiled/__init__.py
impgrpc/compiled/federate.proto
impgrpc/compiled/federate_pb2.py
impgrpc/compiled/federate_pb2_grpc.py
impgrpc/compiled/google/api/annotations.proto
impgrpc/compiled/google/api/annotations_pb2.py
impgrpc/compiled/google/api/annotations_pb2_grpc.py
impgrpc/compiled/google/api/http.proto
impgrpc/compiled/google/api/http_pb2.py
impgrpc/compiled/google/api/http_pb2_grpc.py
impgrpc/compiled/lightning.proto
impgrpc/compiled/lightning_pb2.py
impgrpc/compiled/lightning_pb2_grpc.py
impgrpc/compiled/messaging.proto
impgrpc/compiled/messaging_pb2.py
impgrpc/compiled/messaging_pb2_grpc.py
impgrpc/compiled/protoc-gen-openapiv2/options/annotations.proto
impgrpc/compiled/protoc-gen-openapiv2/options/openapiv2.proto
impgrpc/compiled/protoc_gen_openapiv2/options/annotations_pb2.py
impgrpc/compiled/protoc_gen_openapiv2/options/annotations_pb2_grpc.py
impgrpc/compiled/protoc_gen_openapiv2/options/openapiv2_pb2.py
impgrpc/compiled/protoc_gen_openapiv2/options/openapiv2_pb2_grpc.py
impgrpc/compiled/signing.proto
impgrpc/compiled/signing_pb2.py
impgrpc/compiled/signing_pb2_grpc.py
impgrpc/compiled/socket.proto
impgrpc/compiled/socket_pb2.py
impgrpc/compiled/socket_pb2_grpc.py
impgrpc/compiled/vpn.proto
impgrpc/compiled/vpn_pb2.py
impgrpc/compiled/vpn_pb2_grpc.py
impgrpc/compiled/websocket.proto
impgrpc/compiled/websocket_pb2.py
impgrpc/compiled/websocket_pb2_grpc.py
impgrpc/errors.py
imp_grpc_client-0.0.2.dist-info/LICENSE
imp_grpc_client-0.0.2.dist-info/WHEEL
imp_grpc_client-0.0.2.dist-info/METADATA
imp_grpc_client-0.0.2.dist-info/RECORD
